setup.cfg
setup.py
ndl/__init__.py
ndl/cli.py
ndl/filters.py
ndl/utils.py
ndl.egg-info/PKG-INFO
ndl.egg-info/SOURCES.txt
ndl.egg-info/dependency_links.txt
ndl.egg-info/entry_points.txt
ndl.egg-info/requires.txt
ndl.egg-info/top_level.txt