Metadata-Version: 1.1
Name: ndl
Version: 0.1
Summary: Easy file searching from the command-line
Home-page: https://github.com/msull/needle
Author: Sully Sullenberger
Author-email: sully@sadburger.com
License: UNKNOWN
Download-URL: https://github.com/msull/needle/tarball/0.1
Keywords: search,files,terminal
Platform: UNKNOWN
